[{"children":[{"children":[{"dateAdded":1573628489753,"id":"524","index":0,"parentId":"504","title":"福州大学对外合作与交流处 港澳台事务办公室-通知公告","url":"http://oce.fzu.edu.cn/html/xwzx/tzgg/2017/03/31/0bf3e2e1-d157-4889-9ef3-24e515b6f054.html"},{"dateAdded":1573628489754,"id":"525","index":1,"parentId":"504","title":"bet365 - 在线体育投注","url":"https://www.bet365.com/?&cb=1032641525#/AC/B13/C1/D50/E20537561/F1/"},{"dateAdded":1573628489754,"id":"526","index":2,"parentId":"504","title":"(6 条消息)参加Robomasters 2016夏令营是怎样一种体验? - 知乎","url":"https://www.zhihu.com/question/49986388"},{"dateAdded":1573628489754,"id":"527","index":3,"parentId":"504","title":"WikiLeaks","url":"https://wikileaks.org/"},{"dateAdded":1573628489754,"id":"528","index":4,"parentId":"504","title":"大疆无人机的技术核心是什么？成为大疆的工程师需要具备哪些素质和能力？ - 知乎","url":"https://www.zhihu.com/question/24492974"},{"dateAdded":1573628489755,"id":"529","index":5,"parentId":"504","title":"GitHub - getlantern","url":"https://github.com/getlantern/forum#%E8%93%9D%E7%81%AFlantern%E6%9C%80%E6%96%B0%E7%89%88%E6%9C%AC%E4%B8%8B%E8%BD%BD"},{"dateAdded":1573628489755,"id":"530","index":6,"parentId":"504","title":"Displaying Flight Trajectory Data - Video - MATLAB","url":"https://cn.mathworks.com/videos/displaying-flight-trajectory-data-68741.html"},{"dateAdded":1573628489755,"id":"531","index":7,"parentId":"504","title":"Download eslpod.com American ESL podcasts archive 12-536 mp3 txt fb2 Torrent - Kickass Torrents","url":"https://kickass.cd/eslpod-com-american-esl-podcasts-archive-12-536-mp3-txt-fb2-tt5202806.html"},{"dateAdded":1573628489755,"id":"532","index":8,"parentId":"504","title":"你极力推荐的 Chrome 扩展有哪些？ - CSDN博客","url":"http://blog.csdn.net/garfielder007/article/details/54354619"},{"dateAdded":1573628489755,"id":"533","index":9,"parentId":"504","title":"蓝灯 ","url":"https://getlantern.org/zh_CN/"},{"dateAdded":1573628489756,"id":"534","index":10,"parentId":"504","title":"Chrome 网上应用店 - 扩展程序","url":"https://chrome.google.com/webstore/category/extensions?utm_campaign=en&utm_source=en-et-na-us-oc-webstrhm&utm_medium=et"},{"children":[{"dateAdded":1573628489769,"id":"637","index":0,"parentId":"535","title":"麻省理工公开课：线性代数_全35集_网易公开课","url":"http://open.163.com/special/opencourse/daishu.html"},{"dateAdded":1573628489769,"id":"638","index":1,"parentId":"535","title":"我们需要怎样的数学教育","url":"http://www.matrix67.com/blog/archives/4294"},{"dateAdded":1573628489769,"id":"639","index":2,"parentId":"535","title":"(17 条消息)有哪些值得推荐的线性代数入门书籍？ - 知乎","url":"https://www.zhihu.com/question/19869518"},{"dateAdded":1573628489769,"id":"640","index":3,"parentId":"535","title":"(17 条消息)如何评价Gilbert Strang的线性代数教材《Introduction to Linear Algebra》？ - 知乎","url":"https://www.zhihu.com/question/27633508"},{"dateAdded":1573628489769,"id":"641","index":4,"parentId":"535","title":"Introduction to Linear Algebra, 5th Edition","url":"http://math.mit.edu/~gs/linearalgebra/"},{"dateAdded":1573628489769,"id":"642","index":5,"parentId":"535","title":"矩阵转置偏导数_百度文库","url":"https://wenku.baidu.com/view/f7fa307a580216fc700afdb9.html"},{"dateAdded":1573628489769,"id":"643","index":6,"parentId":"535","title":"中科院研究生课程：矩阵分析(Matrix Analysis)_哔哩哔哩 (゜-゜)つロ 干杯~-bilibili","url":"https://www.bilibili.com/video/av19708226/"},{"children":[],"dateAdded":1573628489770,"dateGroupModified":1573628489770,"id":"644","index":7,"parentId":"535","title":"新建文件夹"}],"dateAdded":1573628489756,"dateGroupModified":1573628489770,"id":"535","index":11,"parentId":"504","title":"线性代数"},{"children":[{"dateAdded":1573628489770,"id":"645","index":0,"parentId":"536","title":"《C++语言程序设计 第3版 学生用书 （清华大学计算机基础教育课程系列教材）》(郑莉)【简介_书评_在线阅读】 - 当当图书","url":"http://product.dangdang.com/8880276.html"},{"dateAdded":1573628489770,"id":"646","index":1,"parentId":"536","title":"中文版：Linux C/C++编程一站式学习 — akabook 3.0 documentation","url":"http://songjinshan.com/akabook/zh/index.html"},{"dateAdded":1573628489770,"id":"647","index":2,"parentId":"536","title":"Stack Overflow","url":"https://stackoverflow.com/questions"},{"dateAdded":1573628489770,"id":"648","index":3,"parentId":"536","title":"麻省理工学院公开课：计算机科学及编程导论_课程目标，数据类型，运算，变量_网易公开课","url":"http://open.163.com/movie/2010/6/D/6/M6TCSIN1U_M6TCSTQD6.html"},{"dateAdded":1573628489770,"id":"649","index":4,"parentId":"536","title":"嵌嵌论坛|DSP论坛|ARM论坛|嵌入式论坛|研旭官方论坛|f28335开发板|单片机论坛 - Powered by Discuz!","url":"http://www.armdsp.net/forum.php"},{"dateAdded":1573628489770,"id":"650","index":5,"parentId":"536","title":"[Wandbox]三へ( へ՞ਊ ՞)へ ﾊｯﾊｯ","url":"https://wandbox.org/"},{"dateAdded":1573628489770,"id":"651","index":6,"parentId":"536","title":"Coliru","url":"http://coliru.stacked-crooked.com/"},{"dateAdded":1573628489770,"id":"652","index":7,"parentId":"536","title":"Online C++ Compiler - Online C++ Editor - Online C++ IDE - C++ Coding Online - Practice C++ Online - Execute C++ Online - Compile C++ Online - Run C++ Online","url":"https://www.tutorialspoint.com/compile_cpp_online.php"}],"dateAdded":1573628489756,"dateGroupModified":1573628489770,"id":"536","index":12,"parentId":"504","title":"c++"},{"children":[{"dateAdded":1573628489771,"id":"653","index":0,"parentId":"537","title":"自动控制理论（1）（自主模式）-学堂在线-最大的中文慕课（mooc）平台","url":"http://www.xuetangx.com/courses/course-v1:TsinghuaX+40250074X+sp/about"},{"dateAdded":1573628489771,"id":"654","index":1,"parentId":"537","title":"CCS6.2超详细使用方法 - 火山LF的博客 - CSDN博客","url":"http://blog.csdn.net/qq_31389903/article/details/53413015"},{"dateAdded":1573628489771,"id":"655","index":2,"parentId":"537","title":"用PID算法反馈控制直流电机_图文_百度文库","url":"https://wenku.baidu.com/view/985350c7cc22bcd127ff0c04.html"},{"dateAdded":1573628489771,"id":"656","index":3,"parentId":"537","title":"如何通俗地解释 PID 参数整定？ - 知乎","url":"https://www.zhihu.com/question/23088613"}],"dateAdded":1573628489757,"dateGroupModified":1573628489771,"id":"537","index":13,"parentId":"504","title":"控制"},{"children":[{"dateAdded":1573628489771,"id":"657","index":0,"parentId":"538","title":"DSP资源分享贴 - Carlos·Wei - 博客园","url":"http://www.cnblogs.com/sigma0/p/6862032.html"},{"dateAdded":1573628489771,"id":"658","index":1,"parentId":"538","title":"CCS6.0环境搭建_百度文库","url":"https://wenku.baidu.com/view/c854b690ddccda38366baf6d.html"},{"dateAdded":1573628489771,"id":"659","index":2,"parentId":"538","title":"Troubleshooting CCS - Texas Instruments Wiki","url":"http://processors.wiki.ti.com/index.php/Troubleshooting_CCS"},{"dateAdded":1573628489772,"id":"660","index":3,"parentId":"538","title":"Category:CCS Training - Texas Instruments Wiki","url":"http://processors.wiki.ti.com/index.php/Category:CCS_Training"},{"dateAdded":1573628489772,"id":"661","index":4,"parentId":"538","title":"SDO-Web/SDOWP - IBM Rational ClearQuest","url":"https://cqweb.ext.ti.com/cqweb/#/SDO-Web/SDOWP&format=HTML&version=cqwj"},{"dateAdded":1573628489772,"id":"662","index":5,"parentId":"538","title":"请先阅读：CCS论坛使用指南 - Code Composer论坛 - Code Composer Studio - 德州仪器E2E社区","url":"https://e2e.ti.com/support/development_tools/code_composer_studio/f/81/t/3131"}],"dateAdded":1573628489757,"dateGroupModified":1573629735052,"id":"538","index":14,"parentId":"504","title":"DSP"}],"dateAdded":1573628489745,"dateGroupModified":1573628489757,"id":"504","index":0,"parentId":"1","title":"其他书签"},{"children":[{"dateAdded":1573628489757,"id":"539","index":0,"parentId":"505","title":"word choice - \"Result in\" or \"result to\" - English Language & Usage Stack Exchange","url":"https://english.stackexchange.com/questions/35305/result-in-or-result-to"},{"dateAdded":1573628489757,"id":"540","index":1,"parentId":"505","title":"老友记第一季（MP3+LRC）在线收听_VOA英语学习网","url":"http://www.tingvoa.com/daxueyingyu/Friends/Friends1/"}],"dateAdded":1573628489745,"dateGroupModified":1573628489757,"id":"505","index":1,"parentId":"1","title":"English"},{"children":[{"dateAdded":1573628489757,"id":"541","index":0,"parentId":"506","title":"专栏：【OpenCV】入门教程 - CSDN博客","url":"http://blog.csdn.net/column/details/opencv-tutorial.html"},{"dateAdded":1573628489757,"id":"542","index":1,"parentId":"506","title":"冈萨雷斯书配套网站","url":"http://www.imageprocessingplace.com/"},{"dateAdded":1573628489758,"id":"543","index":2,"parentId":"506","title":"安装opencv3.0后出现未声明的标识符的解决办法_百度经验","url":"https://jingyan.baidu.com/article/49711c6150f16afa441b7c21.html"},{"dateAdded":1573628489758,"id":"544","index":3,"parentId":"506","title":"OpenCV学习笔记（一）——OpenCV3.1.0+VS2015开发环境配置 - 何乐不为~ - 博客园","url":"https://www.cnblogs.com/linshuhe/p/5764394.html"},{"dateAdded":1573628489758,"id":"545","index":4,"parentId":"506","title":"ImageNet","url":"http://www.image-net.org/"},{"dateAdded":1573628489758,"id":"546","index":5,"parentId":"506","title":"(19 条消息)图像处理 - 知乎","url":"https://www.zhihu.com/topic/19556376/top-answers"},{"dateAdded":1573628489758,"id":"547","index":6,"parentId":"506","title":"计算机视觉新手入门：大佬推荐我这样学习 - CSDN博客","url":"https://blog.csdn.net/u013341341/article/details/79639670"},{"dateAdded":1573628489758,"id":"548","index":7,"parentId":"506","title":"CVPR 2018最佳论文解读：探秘任务迁移学习","url":"https://zhuanlan.zhihu.com/p/38480946"},{"dateAdded":1573628489758,"id":"549","index":8,"parentId":"506","title":"ICCV2017 | 一文详解GAN之父Ian Goodfellow 演讲《生成对抗网络的原理与应用》（附完整PPT） - CSDN博客","url":"https://blog.csdn.net/dQCFKyQDXYm3F8rB0/article/details/78328212"},{"dateAdded":1573628489758,"id":"550","index":9,"parentId":"506","title":"用于部分迁移学习的加权对抗网络 | CVPR 2018论文解读 - CSDN博客","url":"https://blog.csdn.net/c9Yv2cf9I06K2A9E/article/details/79911316"},{"dateAdded":1573628489758,"id":"551","index":10,"parentId":"506","title":"CVPR2018迁移学习相关论文 - CSDN博客","url":"https://blog.csdn.net/cp_oldy/article/details/82183813"}],"dateAdded":1573628489746,"dateGroupModified":1573628489758,"id":"506","index":2,"parentId":"1","title":"计算机视觉"},{"children":[{"dateAdded":1573628489759,"id":"552","index":0,"parentId":"507","title":"OfficePLUS，微软Office官方在线模板网站！","url":"http://www.officeplus.cn/List.shtml?cat=PPT&tag=1"},{"dateAdded":1573628489759,"id":"553","index":1,"parentId":"507","title":"高清大图图片","url":"https://pixabay.com/zh/%E6%9E%B6%E6%9E%84-%E9%92%A2%E5%8E%82-%E5%8E%82%E5%8C%BA%E5%BB%BA%E8%AE%BE-%E8%80%81-%E5%B7%A5%E5%8E%82-%E8%A1%8C%E4%B8%9A-%E5%B7%A5%E4%B8%9A%E5%BB%BA%E7%AD%91-%E7%A6%BB%E5%BC%80-2267789/"},{"dateAdded":1573628489759,"id":"554","index":2,"parentId":"507","title":"自定义地图 | 高德地图API","url":"https://lbs.amap.com/getting-started/mapstyle"},{"dateAdded":1573628489759,"id":"555","index":3,"parentId":"507","title":"鹿班 - 让设计更美好","url":"https://luban.aliyun.com/"},{"dateAdded":1573628489759,"id":"556","index":4,"parentId":"507","title":"用户作品管理|MAKA","url":"http://maka.im/project/myproject"}],"dateAdded":1573628489747,"dateGroupModified":1573628489759,"id":"507","index":3,"parentId":"1","title":"PPT"},{"children":[{"dateAdded":1573628489759,"id":"557","index":0,"parentId":"508","title":"(19 条消息)CNN(卷积神经网络)、RNN(循环神经网络)、DNN(深度神经网络)的内部网络结构有什么区别？ - 知乎","url":"https://www.zhihu.com/question/34681168/answer/84061846"},{"dateAdded":1573628489759,"id":"558","index":1,"parentId":"508","title":"rcnn学习笔记:Rich feature hierarchies for accurate object detection and semantic segmentation - CSDN博客","url":"https://blog.csdn.net/liyaohhh/article/details/50824226"},{"dateAdded":1573628489760,"id":"559","index":2,"parentId":"508","title":"技术向：一文读懂卷积神经网络CNN - 莫小 - 博客园","url":"https://www.cnblogs.com/nsnow/p/4562308.html"},{"dateAdded":1573628489760,"id":"560","index":3,"parentId":"508","title":"RCNN目标检测--Rich feature hierarchies for accurate object detection and semantic segmentation(CVPR 2014) - Zhao-Pace - 博客园","url":"https://www.cnblogs.com/zhao441354231/p/6094990.html"},{"dateAdded":1573628489760,"id":"561","index":4,"parentId":"508","title":"三年来，CNN在图像分割领域经历了怎样的技术变革？ | 雷锋网","url":"https://www.leiphone.com/news/201704/GEJU2kNeqGDpizN2.html"},{"dateAdded":1573628489760,"id":"562","index":5,"parentId":"508","title":"举世瞩目的「深度神经网络」如何应用于移动端？ - CSDN博客","url":"https://blog.csdn.net/dev_csdn/article/details/79136840"},{"dateAdded":1573628489760,"id":"563","index":6,"parentId":"508","title":"笔记︱集成学习Ensemble Learning与树模型、Bagging 和 Boosting、模型融合 - 素质云笔记/Recorder... - CSDN博客","url":"https://blog.csdn.net/sinat_26917383/article/details/54667077"}],"dateAdded":1573628489748,"dateGroupModified":1573628489760,"id":"508","index":4,"parentId":"1","title":"神经网络"},{"children":[{"dateAdded":1573628489760,"id":"564","index":0,"parentId":"509","title":"UFLDL教程 - Ufldl","url":"http://ufldl.stanford.edu/wiki/index.php/UFLDL%E6%95%99%E7%A8%8B"},{"dateAdded":1573628489760,"id":"565","index":1,"parentId":"509","title":"搜索 - 网易云课堂","url":"https://study.163.com/courses-search?keyword=%E5%90%B4%E6%81%A9%E8%BE%BE"},{"dateAdded":1573628489761,"id":"566","index":2,"parentId":"509","title":"(一)深度学习基础(基本概念、优化算法、初始化、正则化等)","url":"https://zhuanlan.zhihu.com/p/31561570"},{"dateAdded":1573628489761,"id":"567","index":3,"parentId":"509","title":"直观梳理深度学习","url":"https://zhuanlan.zhihu.com/c_145288300"},{"dateAdded":1573628489761,"id":"568","index":4,"parentId":"509","title":"4.3. 预处理数据 -","url":"https://sklearn.apachecn.org/#/docs/59"},{"dateAdded":1573628489761,"id":"569","index":5,"parentId":"509","title":"人工智能实践：Tensorflow笔记_中国大学MOOC(慕课)","url":"https://www.icourse163.org/learn/PKU-1002536002?tid=1003797005#/learn/content"},{"dateAdded":1573628489761,"id":"570","index":6,"parentId":"509","title":"核心网络层 - Keras 中文文档","url":"https://keras.io/zh/layers/core/"},{"dateAdded":1573628489761,"id":"571","index":7,"parentId":"509","title":"潘小榭","url":"https://panxiaoxie.cn/page/8/"},{"dateAdded":1573628489761,"id":"572","index":8,"parentId":"509","title":"(5 条消息) Batch normalization和Instance normalization的对比？ - 知乎","url":"https://www.zhihu.com/question/68730628"},{"dateAdded":1573628489761,"id":"573","index":9,"parentId":"509","title":"Bright LGM's Blog","url":"http://brightliao.me/"}],"dateAdded":1573628489748,"dateGroupModified":1573628489761,"id":"509","index":5,"parentId":"1","title":"深度学习"},{"children":[{"dateAdded":1573628489761,"id":"574","index":0,"parentId":"510","title":"Scipy Lecture Notes — Scipy lecture notes","url":"https://www.scipy-lectures.org/"},{"dateAdded":1573628489761,"id":"575","index":1,"parentId":"510","title":"NumPy 教程 | 菜鸟教程","url":"http://www.runoob.com/numpy/numpy-tutorial.html"},{"dateAdded":1573628489762,"id":"576","index":2,"parentId":"510","title":"Python Tutorial: Learn Python For Free | Codecademy","url":"https://www.codecademy.com/learn/learn-python"},{"dateAdded":1573628489762,"id":"577","index":3,"parentId":"510","title":"数据结构与算法python版PegasusWang/python_data_structures_and_algorithms: Python 中文数据结构和算法教程","url":"https://github.com/PegasusWang/python_data_structures_and_algorithms"},{"dateAdded":1573628489762,"id":"578","index":4,"parentId":"510","title":"数据结构python版知乎电子书树与二叉树 - Python 数据结构与算法视频教程","url":"https://python-data-structures-and-algorithms.readthedocs.io/zh/latest/14_%E6%A0%91%E4%B8%8E%E4%BA%8C%E5%8F%89%E6%A0%91/tree/"}],"dateAdded":1573628489748,"dateGroupModified":1573628489762,"id":"510","index":6,"parentId":"1","title":"Python"},{"children":[{"dateAdded":1573628489762,"id":"579","index":0,"parentId":"511","title":"【目录】【中文】【deplearning.ai】【吴恩达课后作业目录】 - 何宽的博客 - CSDN博客","url":"https://blog.csdn.net/u013733326/article/details/79827273"},{"dateAdded":1573628489762,"id":"580","index":1,"parentId":"511","title":"GitHub - arslansadiq/Deep-Learning-Specialization: This repository contains all the work done by me for Coursera's Deep Learning Specialization.","url":"https://github.com/arslansadiq/Deep-Learning-Specialization"},{"dateAdded":1573628489762,"id":"581","index":2,"parentId":"511","title":"1GitHub - stormstone/deeplearning.ai: deeplearning.ai , By Andrew Ng, All slide and notebook + code and some material.","url":"https://github.com/stormstone/deeplearning.ai"},{"dateAdded":1573628489762,"id":"582","index":3,"parentId":"511","title":"Deep-Learning-Specialization/Course 1- Neural Networks and Deep Learning at master · arslansadiq/Deep-Learning-Specialization · GitHub","url":"https://github.com/arslansadiq/Deep-Learning-Specialization/tree/master/Course%201-%20Neural%20Networks%20and%20Deep%20Learning"},{"dateAdded":1573628489762,"id":"583","index":4,"parentId":"511","title":"吴恩达Deeplearning.ai课程学习全体验：深度学习必备课程 | 机器之心","url":"https://www.jiqizhixin.com/articles/2017-08-14-6"},{"dateAdded":1573628489762,"id":"584","index":5,"parentId":"511","title":"网易云课堂 - 我的职业课堂","url":"https://study.163.com/"},{"dateAdded":1573628489763,"id":"585","index":6,"parentId":"511","title":"4卷积神经网络 - 网易云课堂","url":"https://mooc.study.163.com/learn/2001281004?tid=2001392030#/learn/content"},{"dateAdded":1573628489763,"id":"586","index":7,"parentId":"511","title":"序列模型 - 网易云课堂","url":"https://mooc.study.163.com/learn/2001280005?tid=2001391038&_trace_c_p_k2_=c82b149c09fe48508a4e2ea3e0dcf89f#/learn/announce"},{"dateAdded":1573628489763,"id":"587","index":8,"parentId":"511","title":"刘建平Pinard - 博客园","url":"https://www.cnblogs.com/pinard/"},{"dateAdded":1573628489763,"id":"588","index":9,"parentId":"511","title":"keras的主要模块介绍 - LikeTech - CSDN博客","url":"https://blog.csdn.net/lk7688535/article/details/52862377"},{"dateAdded":1573628489763,"id":"589","index":10,"parentId":"511","title":"Stanford University: Tensorflow for Deep Learning Research","url":"https://web.stanford.edu/class/cs20si/"},{"dateAdded":1573628489763,"id":"590","index":11,"parentId":"511","title":"(14) Tensorflow for Deep Learning Research - Lecture 1 - YouTube","url":"https://www.youtube.com/watch?v=g-EvyKpZjmQ&list=PLQ0sVbIj3URf94DQtGPJV629ctn2c1zN-"},{"dateAdded":1573628489763,"id":"591","index":12,"parentId":"511","title":"(1 封私信 / 12 条消息) 如何入门Keras？ - 知乎","url":"https://www.zhihu.com/question/51767944"}],"dateAdded":1573628489749,"dateGroupModified":1573628489763,"id":"511","index":7,"parentId":"1","title":"吴恩达深度学习课程"},{"children":[{"dateAdded":1573628489763,"id":"592","index":0,"parentId":"512","title":"(4条消息)tensorflow下用LSTM网络进行时间序列预测 - 真梦行路的博客 - CSDN博客","url":"https://blog.csdn.net/qq_27280237/article/details/82021222"},{"dateAdded":1573628489763,"id":"593","index":1,"parentId":"512","title":"现已公开的数据集汇总 | TwistedW's Home","url":"http://www.twistedwg.com/2018/04/09/download-dataset.html"},{"dateAdded":1573628489764,"id":"594","index":2,"parentId":"512","title":"Zzlmyself1994/PMSM-based-GAN-and-VAE: Fault Diagnosis of Interturn short circuit of Permanent Magnet Synchronous Motor based on Depth Learning","url":"https://github.com/Zzlmyself1994/PMSM-based-GAN-and-VAE"},{"dateAdded":1573628489764,"id":"595","index":3,"parentId":"512","title":"哈工大张伟 ZhangWei1993/Mechanical-Fault-Diagnosis-Based-on-Deep-Learning: CNN for mechanical fault diagnosis","url":"https://github.com/ZhangWei1993/Mechanical-Fault-Diagnosis-Based-on-Deep-Learning"},{"dateAdded":1573628489764,"id":"596","index":4,"parentId":"512","title":"复现张伟第三章模型AaronCosmos/wdcnn_bearning_fault_diagnosis: wdcnn轴承故障模型","url":"https://github.com/AaronCosmos/wdcnn_bearning_fault_diagnosis"},{"dateAdded":1573628489764,"id":"597","index":5,"parentId":"512","title":"同行基于深度学习的轴承故障识别 - Jiali Zhang的博客 - CSDN博客","url":"https://blog.csdn.net/zhangjiali12011/article/details/88087437"},{"dateAdded":1573628489764,"id":"598","index":6,"parentId":"512","title":"神经网络与深度学习","url":"https://nndl.github.io/"},{"dateAdded":1573628489764,"id":"599","index":7,"parentId":"512","title":"bn层中训练和测试改写 - lien0906的专栏 - CSDN博客","url":"https://blog.csdn.net/lien0906/article/details/78056728"},{"dateAdded":1573628489764,"id":"600","index":8,"parentId":"512","title":"分类页面","url":"http://www.yansongsong.cn/sort-1.html"},{"dateAdded":1573628489764,"id":"601","index":9,"parentId":"512","title":"旋转机械故障诊断公开数据集整理 - hustcxl的博客 - CSDN博客","url":"https://blog.csdn.net/hustcxl/article/details/89394428"},{"dateAdded":1573628489765,"id":"602","index":10,"parentId":"512","title":"Biao Wang雷亚国实验室博士","url":"http://biaowang.tech/publications/"},{"dateAdded":1573628489765,"id":"603","index":11,"parentId":"512","title":"雷亚国西交主页","url":"http://gr.xjtu.edu.cn/web/yaguolei/main"},{"dateAdded":1573628489765,"id":"604","index":12,"parentId":"512","title":"雷亚国学术之门主页","url":"https://www.researchgate.net/profile/Yaguo_Lei"},{"dateAdded":1573628489765,"id":"605","index":13,"parentId":"512","title":"Femto-st - Sciences & Technologies | A European-scale research laboratory","url":"https://www.femto-st.fr/en"},{"dateAdded":1573628489765,"id":"606","index":14,"parentId":"512","title":"(8条消息)卷积神经网络中十大拍案叫绝的操作：卷积核大小好处、变形卷积、可分离卷积等 - 别说话写代码的博客 - CSDN博客","url":"https://blog.csdn.net/qq_21997625/article/details/84899956"},{"dateAdded":1573628489765,"id":"607","index":15,"parentId":"512","title":"(8条消息)【深度学习】经典网络-(InceptionV1)GoogLeNet网络复现(使用Tensorflow实现) - shankezh的博客 - CSDN博客","url":"https://blog.csdn.net/shankezh/article/details/88311788"},{"dateAdded":1573629735052,"id":"663","index":16,"parentId":"512","title":"insightface源码中arcface代码段理解 - 程序员大本营","url":"http://www.pianshen.com/article/1267169696/"},{"dateAdded":1573740926536,"id":"665","index":17,"parentId":"512","title":"（原）InsightFace及其mxnet代码 - darkknightzh - 博客园","url":"https://www.cnblogs.com/darkknightzh/p/8525287.html"},{"dateAdded":1573740929730,"id":"666","index":18,"parentId":"512","title":"(8条消息)insightface中关于arcface损失函数的解释 - Lavi的专栏 - CSDN博客","url":"https://blog.csdn.net/liuweiyuxiang/article/details/90113549"},{"dateAdded":1573923272349,"id":"668","index":19,"parentId":"512","title":"MMDpytouch实现【代码阅读】最大均值差异（Maximum Mean Discrepancy, MMD）损失函数代码解读（Pytroch版） - a529975125的博客 - CSDN博客","url":"https://blog.csdn.net/a529975125/article/details/81176029"},{"dateAdded":1573923870885,"id":"669","index":20,"parentId":"512","title":"Pytorch模型及权重转为Keras - xiaoxifei的专栏 - CSDN博客","url":"https://blog.csdn.net/xiaoxifei/article/details/82685298"},{"dateAdded":1573923889985,"id":"670","index":21,"parentId":"512","title":"一行代码切换TensorFlow与PyTorch，模型训练也能用俩框架","url":"http://baijiahao.baidu.com/s?id=1639028277077254350&wfr=spider&for=pc"},{"dateAdded":1574271695223,"id":"672","index":22,"parentId":"512","title":"工业大数据产业创新平台轴承全生命周期数据下载","url":"http://industrial-bigdata.com/pages/datadown/dataset/dataSet10.jsp?index=2"},{"dateAdded":1574311164351,"id":"674","index":23,"parentId":"512","title":"indrnn独立循环神经网络(indRNN) - wsp_1138886114的博客 - CSDN博客","url":"https://blog.csdn.net/wsp_1138886114/article/details/81910788"},{"dateAdded":1574610852096,"id":"677","index":24,"parentId":"512","title":"一维卷积图解tf.layers.conv1d函数解析（一维卷积） - 233彭于晏的博客 - CSDN博客","url":"https://blog.csdn.net/khy19940520/article/details/89934335"},{"dateAdded":1574745448918,"id":"678","index":25,"parentId":"512","title":"零基础入门深度学习(6) - 长短时记忆网络(LSTM) - 作业部落 Cmd Markdown 编辑阅读器","url":"https://zybuluo.com/hanbingtao/note/581764"},{"dateAdded":1574792943676,"id":"679","index":26,"parentId":"512","title":"围绕曲线生成随机点 – MATLAB中文论坛","url":"https://www.ilovematlab.cn/thread-466717-1-1.html"},{"dateAdded":1574963164963,"id":"680","index":27,"parentId":"512","title":"(8条消息)小波与小波包、小波包分解与信号重构、小波包能量特征提取 暨 小波包分解后实现按频率大小分布重新排列(Matlab 程序详解） - cqfdcw的博客 - CSDN博客","url":"https://blog.csdn.net/cqfdcw/article/details/84995904"}],"dateAdded":1573628489749,"dateGroupModified":1575211202947,"id":"512","index":8,"parentId":"1","title":"故障诊断及预测"},{"children":[{"dateAdded":1573628489765,"id":"608","index":0,"parentId":"513","title":"山东大学-学生就业创业指导中心","url":"http://www.job.sdu.edu.cn/"},{"dateAdded":1573628489765,"id":"609","index":1,"parentId":"513","title":"福建人才联合网--福州大学就业指导中心","url":"http://www.fjrclh.com/"},{"dateAdded":1573628489766,"id":"610","index":2,"parentId":"513","title":"招聘信息","url":"http://jyzd.xmu.edu.cn/platform/require_list?level1=1&level2=0"},{"dateAdded":1573628489766,"id":"611","index":3,"parentId":"513","title":"福州大学招聘日历","url":"http://www.fjrclh.com/calendar/"},{"dateAdded":1573628489766,"id":"612","index":4,"parentId":"513","title":"国家开发银行","url":"http://www.cdb.com.cn/"},{"dateAdded":1573628489766,"id":"613","index":5,"parentId":"513","title":"产品经理导航","url":"http://www.pm265.com/"},{"dateAdded":1573628489766,"id":"614","index":6,"parentId":"513","title":"求职列表 - 白熊求职","url":"https://icebear.me/job.html#0!0!0!1!0!2!!1"},{"dateAdded":1573628489766,"id":"615","index":7,"parentId":"513","title":"中央机关及其直属机构2020年度考试录用公务员专题","url":"http://bm.scs.gov.cn/pp/gkweb/core/web/ui/business/auth/login.html"},{"dateAdded":1573628489766,"id":"616","index":8,"parentId":"513","title":"2017年中国发电行业发电及用电结构变化及产能分析 - 燃煤发电_北极星电力新闻网","url":"http://news.bjx.com.cn/special/?id=856174"},{"dateAdded":1574397217276,"id":"675","index":9,"parentId":"513","title":"2020山东选调生招录信息汇总（省级及市级选调）_","url":"http://xds.offcn.com/sd/ksgg/u27342.html"},{"dateAdded":1575696256999,"id":"685","index":10,"parentId":"513","title":"2019.12.05山东分行面试记录 - 国家开发银行 2020校园招聘 - 应届生求职招聘论坛","url":"https://bbs.yingjiesheng.com/thread-2246844-1-1.html"},{"dateAdded":1575696535414,"id":"686","index":11,"parentId":"513","title":"国家开发银行2019校园招聘综合经验汇总，供2020校招同学参考 - 国家开发银行 2020校园招聘 - 应届生求职招聘论坛","url":"https://bbs.yingjiesheng.com/thread-2206132-1-1.html"},{"dateAdded":1575696932436,"id":"687","index":12,"parentId":"513","title":"国家开发银行 - 第2页 2020校园招聘 - 应届生求职招聘论坛","url":"https://bbs.yingjiesheng.com/forum.php?mod=forumdisplay&fid=266&orderby=dateline&filter=author&orderby=dateline&page=2"}],"dateAdded":1573628489749,"dateGroupModified":1575696932436,"id":"513","index":9,"parentId":"1","title":"job"},{"children":[{"dateAdded":1573628489766,"id":"617","index":0,"parentId":"514","title":"友盟+，国内领先的第三方全域数据智能服务商","url":"https://www.umeng.com/"},{"dateAdded":1573628489766,"id":"618","index":1,"parentId":"514","title":"首页_36氪","url":"https://36kr.com/"},{"dateAdded":1573628489767,"id":"619","index":2,"parentId":"514","title":"虎嗅网","url":"https://www.huxiu.com/"},{"dateAdded":1573628489767,"id":"620","index":3,"parentId":"514","title":"Engadget 中国版 - 消费性电子产品新闻和评测","url":"https://cn.engadget.com/"},{"dateAdded":1573628489767,"id":"621","index":4,"parentId":"514","title":"IT桔子 | 泛互联网创业投资项目信息数据库及商业信息服务商","url":"https://www.itjuzi.com/"},{"dateAdded":1573628489767,"id":"622","index":5,"parentId":"514","title":"百度指数","url":"http://index.baidu.com/v2/index.html?from=pinzhuan#/"},{"dateAdded":1573628489767,"id":"623","index":6,"parentId":"514","title":"易观方舟_大数据用户行为分析平台_助力企业精益成长","url":"https://ark.analysys.cn/?campaign_id=2945008848&utm_campaign=%C6%B7%C5%C6%B1%A3%BB%A4&utm_medium=sem&utm_source=baidu&utm_content=%C6%B7%BB%A4&utm_term=&bd_vid=11031113263831623008"},{"dateAdded":1573628489767,"id":"624","index":7,"parentId":"514","title":"易观方舟_大数据用户行为分析平台_助力企业精益成长","url":"https://ark.analysys.cn/?campaign_id=2945008848&utm_campaign=%C6%B7%C5%C6%B1%A3%BB%A4&utm_medium=sem&utm_source=baidu&utm_content=%C6%B7%BB%A4&utm_term=&bd_vid=11103338408757524152"},{"dateAdded":1573628489767,"id":"625","index":8,"parentId":"514","title":"艾瑞网_互联网数据资讯聚合平台","url":"https://www.iresearch.cn/"},{"dateAdded":1573628489767,"id":"626","index":9,"parentId":"514","title":"人人都是产品经理 | 产品经理、产品爱好者学习交流平台","url":"http://www.woshipm.com/"},{"dateAdded":1573628489768,"id":"627","index":10,"parentId":"514","title":"硅谷早知道","url":"https://coffee.pmcaff.com/"},{"dateAdded":1573628489768,"id":"628","index":11,"parentId":"514","title":"产品壹佰 | 最真实的产品经理学习网站","url":"http://www.chanpin100.com/"},{"dateAdded":1573628489768,"id":"629","index":12,"parentId":"514","title":"虎嗅APP产品分析报告：从思考，到创造 | 人人都是产品经理","url":"http://www.woshipm.com/evaluating/2305006.html"},{"dateAdded":1573628489768,"id":"630","index":13,"parentId":"514","title":"如何正确地画出页面流程图 | 人人都是产品经理","url":"http://www.woshipm.com/rp/651734.html"},{"dateAdded":1573628489768,"id":"631","index":14,"parentId":"514","title":"「36氪」产品分析报告（如果我是PM部分） | 人人都是产品经理","url":"http://www.woshipm.com/pmd/1403730.html"},{"dateAdded":1573628489768,"id":"632","index":15,"parentId":"514","title":"「36氪」 产品分析报告（产品分析部分） | 人人都是产品经理","url":"http://www.woshipm.com/chuangye/1272110.html"},{"dateAdded":1573628489768,"id":"633","index":16,"parentId":"514","title":"「36氪」产品分析报告（竞品分析部分） | 人人都是产品经理","url":"http://www.woshipm.com/evaluating/1304618.html"},{"dateAdded":1573628489768,"id":"634","index":17,"parentId":"514","title":"白熊学院产品经理训练营学习方法总结与心得体会 - 简书","url":"https://www.jianshu.com/p/02240ed28f18"},{"dateAdded":1573628489768,"id":"635","index":18,"parentId":"514","title":"「PM知识体系」系列五：产品分析报告 - 简书","url":"https://www.jianshu.com/p/5ff52d0f6799"},{"dateAdded":1573628489769,"id":"636","index":19,"parentId":"514","title":"产品经理笔试/面试100问（持续更新中） - 简书","url":"https://www.jianshu.com/p/c530935ffa27"}],"dateAdded":1573628489750,"dateGroupModified":1573628489769,"id":"514","index":10,"parentId":"1","title":"产品经理网站"},{"dateAdded":1573628489750,"id":"515","index":11,"parentId":"1","title":"GitHub - Syllo/nvtop: NVIDIA GPUs htop like monitoring tool","url":"https://github.com/Syllo/nvtop"},{"dateAdded":1573628489750,"id":"516","index":12,"parentId":"1","title":"题库 - 力扣 (LeetCode) 全球极客挚爱的技术成长平台","url":"https://leetcode-cn.com/problemset/algorithms/"},{"dateAdded":1573628489751,"id":"517","index":13,"parentId":"1","title":"(4条未读通知) 产品&运营面试题库_牛客网","url":"https://www.nowcoder.com/ta/review-product?query=&asc=true&order=&page=1"},{"dateAdded":1573628489751,"id":"518","index":14,"parentId":"1","title":"(4条未读通知) 产品经理历年公司笔试真题汇总_产品运营_牛客网","url":"https://www.nowcoder.com/discuss/213182?type=all&order=time&pos=&page=0"},{"dateAdded":1573628489752,"id":"519","index":15,"parentId":"1","title":"一只B端产品经理的成长之路_ITPUB博客","url":"http://blog.itpub.net/31557835/viewspace-2636357/"},{"dateAdded":1573628489753,"id":"520","index":16,"parentId":"1","title":"全历史","url":"https://www.allhistory.com/"},{"dateAdded":1573628489753,"id":"521","index":17,"parentId":"1","title":"maka复制|maka一键复制|maka收费模板复制|MAKA复制系统源码|maka模板复制","url":"http://ma.changjing360.com/"},{"dateAdded":1573628489753,"id":"522","index":18,"parentId":"1","title":"发电_产业网搜索_中国产业信息网","url":"https://www.chyxx.com/search?q=%B7%A2%B5%E7"},{"dateAdded":1573628489753,"id":"523","index":19,"parentId":"1","title":"纺织工艺流程 - 百度文库","url":"https://wenku.baidu.com/view/0c9d5a7827284b73f24250bc.html"},{"dateAdded":1573785172992,"id":"667","index":20,"parentId":"1","title":"数字帝国 - 数学工具","url":"https://zh.numberempire.com/"},{"dateAdded":1572252609812,"id":"330","index":21,"parentId":"1","title":"图形计算器 - GeoGebra","url":"https://www.geogebra.org/graphing"},{"dateAdded":1575211202947,"id":"681","index":22,"parentId":"1","title":"Library Genesis: 郭建龙 - 汴京之围: 北宋末年的外交, 战争和人","url":"http://libgen.is/book/index.php?md5=5201494E83C58C44C397D09D100942EE"},{"dateAdded":1575329106651,"id":"683","index":23,"parentId":"1","title":"(8条消息)如何在word中将未经过上标的参考文献全部改为上标形式 - kekuangshuang9528的博客 - CSDN博客","url":"https://blog.csdn.net/kekuangshuang9528/article/details/88080286"}],"dateAdded":1541002421051,"dateGroupModified":1575696256999,"id":"1","index":0,"parentId":"0","title":"书签栏"}]